RequestsLibrary/DeprecatedKeywords.py
RequestsLibrary/RequestsKeywords.py
RequestsLibrary/RequestsOnSessionKeywords.py
RequestsLibrary/SessionKeywords.py
RequestsLibrary/__init__.py
RequestsLibrary/compat.py
RequestsLibrary/exceptions.py
RequestsLibrary/log.py
RequestsLibrary/utils.py
RequestsLibrary/version.py
robotframework_requests-0.9.7.dist-info/LICENSE.md
robotframework_requests-0.9.7.dist-info/METADATA
robotframework_requests-0.9.7.dist-info/WHEEL
robotframework_requests-0.9.7.dist-info/top_level.txt
robotframework_requests-0.9.7.dist-info/RECORD
