Metadata-Version: 2.1
Name: robotframework-requests
Version: 0.9.7
Summary: Robot Framework keyword library wrapper around requests
Home-page: https://github.com/MarketSquare/robotframework-requests
Author: Bulkan Savun Evcimen
Author-email: bulkan@gmail.com
Maintainer: Luca Giovenzana
Maintainer-email: luca@giovenzana.org
License: MIT
Keywords: robotframework testing test automation http client requests rest api
Platform: any
Classifier: Development Status :: 5 - Production/Stable
Classifier: License :: OSI Approved :: MIT License
Classifier: Operating System :: OS Independent
Classifier: Programming Language :: Python
Classifier: Programming Language :: Python :: 2
Classifier: Programming Language :: Python :: 2.7
Classifier: Programming Language :: Python :: 3
Classifier: Programming Language :: Python :: 3.6
Classifier: Programming Language :: Python :: 3.7
Classifier: Programming Language :: Python :: 3.8
Classifier: Programming Language :: Python :: 3.9
Classifier: Topic :: Software Development :: Testing
License-File: LICENSE.md
Requires-Dist: robotframework
Requires-Dist: requests
Provides-Extra: test
Requires-Dist: robotframework>=3.2.1; extra == "test"
Requires-Dist: pytest; extra == "test"
Requires-Dist: flask; extra == "test"
Requires-Dist: six; extra == "test"
Requires-Dist: coverage; extra == "test"
Requires-Dist: flake8; extra == "test"
